{
    "video_id": "1Qnm8OLOSZg",
    "title": "Where Money Goes If Yield Is Banned",
    "channel_url": "ttps://www.youtube.com/@CoinBureau",
    "author": "Coin Bureau",
    "publish_date": "2026-03-23 16:00:03+00:00",
    "feed_id": "d3f4d7b6-d5a2-413c-bbcd-f700f6bc1db2",
    "output_language": "hu",
    "summary": "A videó a hagyományos banki modell fenyegetéséről beszél, amelyet a magas hozamú stabilcoinok terjedése okoz. A Genius Act, amely a digitális eszközök szabályozását célozza, lehetővé tette a stabilcoin kibocsátók számára, hogy ne fizessenek kamatot a token birtokosainak, ami megnyitotta az utat harmadik fél platformok előtt, hogy közvetett hozamot kínáljanak. A bankszektor lobbizása azt célozza, hogy megakadályozza a versenyt a digitális eszközök terén, melyek lehetőséget biztosítanak a befektetők számára a valódi piaci hozamok realizálására, ezáltal erősítve a hagyományos banki modell védelmét. Számos jogi kihívás és ellenállás mutatkozik a decentralizált pénzügyi protokollokkal szemben, mivel a kormány próbálja kordában tartani a piacokat. A videó végén felvetik a kérdést, hogy az ilyen szabályozások szükségesek-e a hagyományos hitelpiac védelméhez, vagy éppen ellenkezőleg, az átmeneti lehetőségek eltűnését sürgetik.",
    "key_points": [
        "A hagyományos banki modell nem fizetnek érdemi kamatot a betéteseknek.",
        "A Genius Act megtiltja a stabilcoin kibocsátóknak, hogy közvetlen hozamot fizessenek.",
        "A bankszektor védekező taktikát alkalmaz a decentralizált pénzügyi piacok ellen."
    ],
    "main_topics": [
        "Hagyományos banki rendszer",
        "Digitális eszközök szabályozása"
    ],
    "chart_values": {
        "sentiment 1": 30
    }
}